tuya2domoticz/__init__.py
tuya2domoticz/__main__.py
tuya2domoticz/t2d_device.py
tuya2domoticz/t2d_devman.py
tuya2domoticz/t2dconnector.py
tuya2domoticz/conf/tuya2domoticz.initd
tuya2domoticz/conf/tuya2domoticz.service
tuya2domoticz-0.0.6.dist-info/LICENSE
tuya2domoticz-0.0.6.dist-info/METADATA
tuya2domoticz-0.0.6.dist-info/WHEEL
tuya2domoticz-0.0.6.dist-info/top_level.txt
tuya2domoticz-0.0.6.dist-info/RECORD
