Metadata-Version: 2.1
Name: tuya2domoticz
Version: 0.0.6
Summary: Tuya sensor subscription for Domoticz
Home-page: https://github.com/costa76/tuya2domoticz
Author: Constantin Petra
Author-email: constantin.petra@gmail.com
License: UNKNOWN
Project-URL: Bug Tracker, https://github.com/costa76/tuya2domoticz/issues
Platform: UNKNOWN
Classifier: Programming Language :: Python :: 3
Classifier: License :: OSI Approved :: MIT License
Classifier: Operating System :: OS Independent
Requires-Python: >=3.6
License-File: LICENSE
Requires-Dist: requests
Requires-Dist: tuya-connector-python
Requires-Dist: python-daemon
